Workbook
Name Coating_Databas: [1]Estimate!#REF!
Name Coating_Databas: Estimate!#REF!

Sheet Estimate
B1: Today's Date: | C1: 45951 | F1: Bill To Address:
B2: Job Name: | C2: Living Waters Church | F2: City, State, Zip:
B3: Job Type: | C3: Coated Foam Roof Restoration | F3: Contact:
B4: Site Address: | C4: 5425 Frankfort Road | F4: Email Address:
B5: City, State, Zip: | C5: Shelbyville, KY 40065 | F5: Phone:
B6: Contact: | C6: Fred Bates | F6: Fax:
B7: Title:
B8: Email Address:
B9: Phone:
A11: Est. Square Feet: | D11: 1.1 | E11: 1.2 | F11: 1.3
A12: Materials | C12: 11058 | D12: =C12*D11 -> 12163.8 | E12: =C12*E11 -> 13269.6 | F12: =C12*F11 -> 14375.4
A13: *
B14: Type | C14: Sq. Ft. | E14: Unit Price | G14: Est. Units | H14: Est. Cost
A16: Foam | B16: Mfg: | C16: Gaco = 1, BASF = 2
B17: Types: | C17: Roof 2.7 = 1
D18: Thickness | F18: Yield
A19: 11 | B19: =IF(A19=11,"Gaco Roof 2.7",IF(A19=21,"BASF Roof 2.7","")) -> Gaco Roof 2.7 | C19: 865 | D19: 1.5 | E19: 2.25 | F19: 2600 | G19: =((C19/F19)*D19)*1000 -> 499.03846 | H19: =E19*G19 -> 1122.8365
A20: 11 | B20: =IF(A20=11,"Gaco Roof 2.7",IF(A20=21,"BASF Roof 2.7","")) -> Gaco Roof 2.7 | C20: 0 | D20: 1.25 | E20: 2.25 | F20: 2900 | G20: =((C20/F20)*D20)*1000 -> 0 | H20: =E20*G20 -> 0
A21: 11 | B21: =IF(A21=11,"Gaco Roof 2.7",IF(A21=21,"BASF Roof 2.7","")) -> Gaco Roof 2.7 | C21: 0 | D21: 1.25 | E21: 2.25 | F21: 2900 | G21: =((C21/F21)*D21)*1000 -> 0 | H21: =E21*G21 -> 0
A23: Coating | B23: Mfg: | C23: Gaco = 1, BASF = 2, AW = 3
B24: Types: | C24: Silicone = 1, Acrylic = 2, Urethane = 3, Aluminum = 4
D25: Gal/Sq.
A26: 11 | B26: =IF(A26=11,"Gaco Silicone",IF(A26=12,"Gaco Acrylic",IF(A26=13,"Gaco Urethane",IF(A26=21,"BASF Silicone",IF(A26=22,"BASF Acrylic",IF(A26=23,"BASF Urethane",IF(A26=4,"Aluminum",IF(A26=31,"AW Silicone",IF(A26=32,"AW Acrylic",IF(A26=33,"AW Urethane","")))))))))) -> Gaco Silicone | C26: 11250 | D26: 1 | E26: 30 | F26: S2100 | G26: =(((C26/100)*D26))*(1+($A$30/100)) -> 129.375 | H26: =E26*G26 -> 3881.25
A27: 11 | B27: =IF(A27=11,"Gaco Silicone",IF(A27=12,"Gaco Acrylic",IF(A27=13,"Gaco Urethane",IF(A27=21,"BASF Silicone",IF(A27=22,"BASF Acrylic",IF(A27=23,"BASF Urethane",IF(A27=4,"Aluminum",IF(A27=31,"AW Silicone",IF(A27=32,"AW Acrylic",IF(A27=33,"AW Urethane","")))))))))) -> Gaco Silicone | C27: 11250 | D27: 1 | E27: 30 | F27: S2100 | G27: =(((C27/100)*D27))*(1+($A$30*0.01)) -> 129.375 | H27: =E27*G27 -> 3881.25
A28: 11 | B28: =IF(A28=11,"Gaco Silicone",IF(A28=12,"Gaco Acrylic",IF(A28=13,"Gaco Urethane",IF(A28=21,"BASF Silicone",IF(A28=22,"BASF Acrylic",IF(A28=23,"BASF Urethane",IF(A28=4,"Aluminum",IF(A28=31,"AW Silicone",IF(A28=32,"AW Acrylic",IF(A28=33,"AW Urethane","")))))))))) -> Gaco Silicone | C28: 0 | D28: 1 | E28: 42 | G28: =(((C28/100)*D28))*(1+($A$30*0.01)) -> 0 | H28: =E28*G28 -> 0
A29: Margin %
A30: 15
A32: Thinner | B32: Types: | C32: Naphtha VM&P = 1, Mineral Spirits = 2, Xylene= 3
A33: 1 | B33: =IF(A33=1,"Naphtha VM&P",IF(A33=2,"Mineral Spirits",IF(A33=3,"Xylene",""))) -> Naphtha VM&P | G33: =((G26+G27+G28)/55)*4 -> 18.818182 | H33: =E33*G33 -> 0
A35: Granules | B35: Types: | C35: 3M = 1, SESCO = 2
A36: 2 | B36: =IF(A36=1,"3M",IF(A36=2,"SESCO","")) -> SESCO | C36: 11300 | E36: 30 | F36: Snow White | G36: =(((C36/100)*50)/100) -> 56.5 | H36: =E36*G36 -> 1695
A38: Primer | B38: Types: | C38: Gaco E-5320 = 1, Red Zinc Oxide = 2, Black Foam = 3
A39: 1 | B39: =IF(A39=1,"Gaco E-5320",IF(A39=2,"Red Zinc Oxide",IF(A39=3,"Black Foam",""))) -> Gaco E-5320 | C39: 865 | E39: 40 | G39: =SUM(C39/250) -> 3.46 | H39: =E39*G39 -> 138.4
A41: Caulk/Sealant | B41: Types: | C41: Silicone Tube = 1, Silicone Sausage = 2, Urethane Tube = 3
C42: Urethane Sausage = 4, Gaco SF-2000 = 5, Buttergrade = 6
A43: 2 | B43: =IF(A43=1,"Silicone Tube",IF(A43=2,"Silicone Sausage",IF(A43=3,"Urethane Tube",IF(A43=4,"Urethane Sausage",IF(A43=5,"Gaco SF-2000",IF(A43=6,"Buttergrade","")))))) -> Silicone Sausage | E43: 12 | G43: 48 | H43: =E43*G43 -> 576
A45: 5 | B45: =IF(A45=1,"Silicone Tube",IF(A45=2,"Silicone Sausage",IF(A45=3,"Urethane Tube",IF(A45=4,"Urethane Sausage",IF(A45=5,"Gaco SF-2000",IF(A45=6,"Buttergrade","")))))) -> Gaco SF-2000 | E45: 46 | G45: 12 | H45: =E45*G45 -> 552
C46: Linear Ft.
A47: Misc./Seams | C47: 0
D48: Units
A49: Penetrations | D49: 0
A51: HVAC Units | D51: 0
A53: Drains | D53: 0
A55: Board Stock | B55: Types: | C55: ISO Board = 1, Wood Fiber = 2, Dens Deck = 3
C56: Type X Gyp Board = 4, Flute Filler = 5
C57: Sq. Ft. | D57: Thickness | E57: Price/Sq.
A58: 1 | B58: =IF(A58=1,"ISO Board",IF(A58=2,"Wood Fiber",IF(A58=3,"Dens Deck",IF(A58=4,"Type X Gyp Board",IF(A58=5,"Flute Filler",""))))) -> ISO Board | C58: 0 | D58: 0 | E58: 30 | H58: =C58/100*E58 -> 0
A59: 1 | B59: =IF(A59=1,"ISO Board",IF(A59=2,"Wood Fiber",IF(A59=3,"Dens Deck",IF(A59=4,"Type X Gyp Board",IF(A59=5,"Flute Filler",""))))) -> ISO Board | C59: 0 | D59: 0 | E59: 30 | H59: =C59/100*E59 -> 0
A60: 1 | B60: =IF(A60=1,"ISO Board",IF(A60=2,"Wood Fiber",IF(A60=3,"Dens Deck",IF(A60=4,"Type X Gyp Board",IF(A60=5,"Flute Filler",""))))) -> ISO Board | C60: 0 | D60: 0 | E60: 30 | H60: =C60/100*E60 -> 0
C62: Length
A63: Fasteners | E63: 100 | G63: =C58/32*12 -> 0 | H63: =E63*G63/1000 -> 0
A65: Plates | E65: 80 | G65: =C58/32*12 -> 0 | H65: =E65*G65/1000 -> 0
A67: Dumpsters | B67: Types: | C67: 20 Yard = 1, 30 Yard = 2, 40 Yard = 3
D68: Thickness | F68: Margin %
A69: 3 | B69: =IF(A69=1,"20 Yard",IF(A69=2,"30 Yard",IF(A69=3,"40 Yard",""))) -> 40 Yard | C69: 0 | D69: 0 | E69: 400 | F69: 25 | G69: =(IF(A69=1,C69*D69/12/700,IF(A69=2,C69*D69/12/1000,IF(A69=3,C69*D69/12/1400,""))))*(1+(F69/100)) -> 0 | H69: =G69*E69 -> 0
A71: Lift | B71: Types: | C71: Forklift = 1, Boom = 2, Scissor = 3, Articulating = 4
C72: Size | D72: Period | F72: Margin %
A73: 1 | B73: =IF(A73=1,"Forklift",IF(A73=2,"Boom",IF(A73=3,"Scissor",IF(A73=4,"Articulating","")))) -> Forklift | C73: 20' | D73: 0 | E73: 0 | F73: 20 | H73: =D73*E73*(1+(F73/100)) -> 0
A74: 1 | B74: =IF(A74=1,"Forklift",IF(A74=2,"Boom",IF(A74=3,"Scissor",IF(A74=4,"Articulating","")))) -> Forklift | C74: 20' | D74: 0 | E74: 0 | F74: 20 | H74: =D74*E74*(1+(F74/100)) -> 0
A76: Delivery Fee | E76: 0 | G76: 0 | H76: =E76*G76 -> 0
C78: Linear Ft. | D78: Width
A79: Fabric | C79: 0 | D79: 0 | E79: 5 | H79: =C79*E79 -> 0
C81: Linear Ft.
A82: Edge Metal | C82: 0 | E82: 0 | H82: =C82*E82 -> 0
A84: Gutter | C84: 0 | E84: 0 | H84: =C84*E84 -> 0
A86: Downspouts | C86: 0 | E86: 0 | H86: =C86*E86 -> 0
A88: Roof Hatch | E88: 0 | G88: 0 | H88: =G88*E88 -> 0
A90: Scuppers | E90: 0 | G90: 0 | H90: =G90*E90 -> 0
A92: Curbs | E92: 0 | G92: 0 | H92: =G92*E92 -> 0
A94: Ladders | E94: 0 | G94: 0 | H94: =G94*E94 -> 0
A96: Pitch Pockets | E96: 0 | G96: 0 | H96: =G96*E96 -> 0
C98: Est. Days
A99: Generator | C99: 7 | E99: 50 | H99: =C99*E99 -> 350
A101: Misc. | E101: 0 | H101: =E101 -> 0
A103: Freight | E103: 0 | H103: =E103 -> 0
B105: No. of Trips | C105: R.T. Miles
A106: Sales/Inspect. | B106: 9 | C106: 20 | E106: 0.75 | H106: =B106*C106*E106 -> 135
A108: Truck Exp. | B108: 16 | C108: 20 | E108: 1 | H108: =B108*C108*E108 -> 320
C109: . | H109: *****************
G110: Subtotal Materials | H110: =SUM(H19:H108) -> 12651.737
F111: Sales Tax % | G111: 0.06 | H111: =(H110*G111) -> 759.10419
A112: Labor / Subcontractor
A113: *
B114: Days | C114: No. of People | D114: Total Hours | E114: Prevailing Wage | F114: Fringe | G114: Total Prevailing Wage | H114: Est. Cost | J114: Daily Rate
A116: Set Up/Safety | B116: 0.15 | C116: 5 | D116: =(B116*People!B11)*C116 -> 7.5 | G116: =(E116+F116)*People!C3 -> 0 | H116: =IF(G116=0, B116*J116, D116*G116) -> 250.0875 | J116: =IF(C116=1,People!$D$12)+IF(C116=2,People!$E$12)+IF(C116=3,People!$F$12)+IF(C116=4,People!$G$12)+IF(C116=5,People!$H$12)+IF(C116=6,People!$I$12)+IF(C116=7,People!$J$12)+IF(C116=8,People!$K$12) -> 1667.25
A118: PW/Prep | B118: 1 | C118: 5 | D118: =(B118*People!B11)*C118 -> 50 | G118: =(E118+F118)*People!C3 -> 0 | H118: =IF(G118=0, B118*J118, D118*G118) -> 1667.25 | J118: =IF(C118=1,People!$D$12)+IF(C118=2,People!$E$12)+IF(C118=3,People!$F$12)+IF(C118=4,People!$G$12)+IF(C118=5,People!$H$12)+IF(C118=6,People!$I$12)+IF(C118=7,People!$J$12)+IF(C118=8,People!$K$12) -> 1667.25
A120: Tear Off & Foam | B120: 1.25 | C120: 5 | D120: =(B120*People!B11)*C120 -> 62.5 | G120: =(E120+F120)*People!C3 -> 0 | H120: =IF(G120=0, B120*J120, D120*G120) -> 2084.0625 | J120: =IF(C120=1,People!$D$12)+IF(C120=2,People!$E$12)+IF(C120=3,People!$F$12)+IF(C120=4,People!$G$12)+IF(C120=5,People!$H$12)+IF(C120=6,People!$I$12)+IF(C120=7,People!$J$12)+IF(C120=8,People!$K$12) -> 1667.25
A122: Base ` | B122: 1.4 | C122: 5 | D122: =(B122*People!B11)*C122 -> 70 | G122: =(E122+F122)*People!C3 -> 0 | H122: =IF(G122=0, B122*J122, D122*G122) -> 2334.15 | J122: =IF(C122=1,People!$D$12)+IF(C122=2,People!$E$12)+IF(C122=3,People!$F$12)+IF(C122=4,People!$G$12)+IF(C122=5,People!$H$12)+IF(C122=6,People!$I$12)+IF(C122=7,People!$J$12)+IF(C122=8,People!$K$12) -> 1667.25
D124: =(B124*People!B11)*C124 -> 0 | G124: =(E124+F124)*People!C3 -> 0 | H124: =IF(G124=0, B124*J124, D124*G124) -> 0 | J124: =IF(C124=1,People!$D$12)+IF(C124=2,People!$E$12)+IF(C124=3,People!$F$12)+IF(C124=4,People!$G$12)+IF(C124=5,People!$H$12)+IF(C124=6,People!$I$12)+IF(C124=7,People!$J$12)+IF(C124=8,People!$K$12) -> 0
A126: Caulk/SF | B126: 0.65 | C126: 5 | D126: =(B126*People!B11)*C126 -> 32.5 | G126: =(E126+F126)*People!C3 -> 0 | H126: =IF(G126=0, B126*J126, D126*G126) -> 1083.7125 | J126: =IF(C126=1,People!$D$12)+IF(C126=2,People!$E$12)+IF(C126=3,People!$F$12)+IF(C126=4,People!$G$12)+IF(C126=5,People!$H$12)+IF(C126=6,People!$I$12)+IF(C126=7,People!$J$12)+IF(C126=8,People!$K$12) -> 1667.25
A128: Details | D128: =(B128*People!B11)*C128 -> 0 | G128: =(E128+F128)*People!C3 -> 0 | H128: =IF(G128=0, B128*J128, D128*G128) -> 0 | J128: =IF(C128=1,People!$D$12)+IF(C128=2,People!$E$12)+IF(C128=3,People!$F$12)+IF(C128=4,People!$G$12)+IF(C128=5,People!$H$12)+IF(C128=6,People!$I$12)+IF(C128=7,People!$J$12)+IF(C128=8,People!$K$12) -> 0
A130: Top Coat/Gran | B130: 1.4 | C130: 5 | D130: =(B130*People!B11)*C130 -> 70 | G130: =(E130+F130)*People!C3 -> 0 | H130: =IF(G130=0, B130*J130, D130*G130) -> 2334.15 | J130: =IF(C130=1,People!$D$12)+IF(C130=2,People!$E$12)+IF(C130=3,People!$F$12)+IF(C130=4,People!$G$12)+IF(C130=5,People!$H$12)+IF(C130=6,People!$I$12)+IF(C130=7,People!$J$12)+IF(C130=8,People!$K$12) -> 1667.25
A132: Touch/Clean Up | B132: 0.5 | C132: 5 | D132: =(B132*People!B11)*C132 -> 25 | G132: =(E132+F132)*People!C3 -> 0 | H132: =IF(G132=0, B132*J132, D132*G132) -> 833.625 | J132: =IF(C132=1,People!$D$12)+IF(C132=2,People!$E$12)+IF(C132=3,People!$F$12)+IF(C132=4,People!$G$12)+IF(C132=5,People!$H$12)+IF(C132=6,People!$I$12)+IF(C132=7,People!$J$12)+IF(C132=8,People!$K$12) -> 1667.25
A134: Misc. | B134: 0.65 | C134: 5 | D134: =(B134*People!B11)*C134 -> 32.5 | G134: =(E134+F134)*People!C3 -> 0 | H134: =IF(G134=0, B134*J134, D134*G134) -> 1083.7125 | J134: =IF(C134=1,People!$D$12)+IF(C134=2,People!$E$12)+IF(C134=3,People!$F$12)+IF(C134=4,People!$G$12)+IF(C134=5,People!$H$12)+IF(C134=6,People!$I$12)+IF(C134=7,People!$J$12)+IF(C134=8,People!$K$12) -> 1667.25
C136: Est. Hours / Day | E136: No. of People | G136: Est. Rate
A137: Loading | C137: 1 | E137: 1 | G137: 25.5 | H137: =C137*E137*G137*B108 -> 408
A139: Traveling | C139: 1 | E139: 5 | G139: 13 | H139: =C139*E139*G139*B108 -> 1040
C141: Est. Hours
A142: Infrared Scan | C142: 0 | E142: 0 | G142: 75 | H142: =C142*E142*G142 -> 0
C144: Est. Days
...

Sheet People
E1: Crew Size
A2: Job Classification | B2: Hourly Wage | C2: Burden Rate | D2: 1 | E2: 2 | F2: 3 | G2: 4 | H2: 5 | I2: 6 | J2: 7 | K2: 8
A3: Foreman / Sprayer | B3: 33 | C3: 1.35 | D3: =B3*C3 -> 44.55 | E3: =B3*C3 -> 44.55 | F3: =B3*C3 -> 44.55 | G3: =B3*C3 -> 44.55 | H3: =B3*C3 -> 44.55 | I3: =B3*C3 -> 44.55 | J3: =B3*C3 -> 44.55 | K3: =B3*C3 -> 44.55
A4: Sprayer / Trailer | B4: 26 | C4: 1.35 | E4: =B4*C4 -> 35.1 | F4: =B4*C4 -> 35.1 | G4: =B4*C4 -> 35.1 | H4: =B4*C4 -> 35.1 | I4: =B4*C4 -> 35.1 | J4: =B4*C4 -> 35.1 | K4: =B4*C4 -> 35.1
A5: Trailer / Hose | B5: 23.5 | C5: 1.35 | F5: =B5*C5 -> 31.725 | G5: =B5*C5 -> 31.725 | H5: =B5*C5 -> 31.725 | I5: =B5*C5 -> 31.725 | J5: =B5*C5 -> 31.725 | K5: =B5*C5 -> 31.725
A6: Hose / Laborer | B6: 21 | C6: 1.35 | G6: =B6*C6 -> 28.35 | H6: =B6*C6 -> 28.35 | I6: =B6*C6 -> 28.35 | J6: =B6*C6 -> 28.35 | K6: =B6*C6 -> 28.35
A7: Laborer | B7: 20 | C7: 1.35 | H7: =B7*C7 -> 27 | I7: =B7*C7 -> 27 | J7: =B7*C7 -> 27 | K7: =B7*C7 -> 27
A8: Laborer | B8: 20 | C8: 1.35 | I8: =B8*C8 -> 27 | J8: =B8*C8 -> 27 | K8: =B8*C8 -> 27
A9: Laborer | B9: 18 | C9: 1.35 | J9: =B9*C9 -> 24.3 | K9: =B9*C9 -> 24.3
A10: Laborer | B10: 18 | C10: 1.35 | K10: =B10*C10 -> 24.3
A11: Hours /Day | B11: 10
A12: Estimated Cost/Day | D12: =SUM(D3:D10)*B11 -> 445.5 | E12: =SUM(E3:E10)*B11 -> 796.5 | F12: =SUM(F3:F10)*B11 -> 1113.75 | G12: =SUM(G3:G10)*B11 -> 1397.25 | H12: =SUM(H3:H10)*B11 -> 1667.25 | I12: =SUM(I3:I10)*B11 -> 1937.25 | J12: =SUM(J3:J10)*B11 -> 2180.25 | K12: =SUM(K3:K10)*B11 -> 2423.25
A15: Crew Leaders | B15: Hourly | C15: Travel
A16: Mariano Perez | B16: 33 | C16: 20
A17: Carlos Garcia | B17: 28 | C17: 20
A18: Abel Reyes | B18: 28 | C18: 20
A19: Miguel Avila | B19: 25 | C19: 10
A21: Workers | B21: Hourly | C21: Travel
A22: Hugo | B22: 28 | C22: 10
A23: Santos | B23: 25 | C23: 20
A24: Erik Avila | B24: 25 | C24: 12.5
A25: Michael | B25: 23.5 | C25: 11.75
A26: Juan Loa | B26: 23 | C26: 10
A27: Axel | B27: 23 | C27: 10
A28: Gilberto Morales | B28: 21 | C28: 8.75
A29: Melvin Lutin | B29: 20 | C29: 8
A30: Ramiro | B30: 20 | C30: 10
A31: Jesus | B31: 20 | C31: 7.25
A32: Onilson Morales | B32: 19.5 | C32: 8
A33: Frederico | B33: 19 | C33: 7.25
A34: Pedro Morales | B34: 18.5 | C34: 8
A37: TEMP Workers | B37: Hourly | C37: Travel
A38: Nelvi | B38: 19 | C38: 7.25
A39: Bryan | B39: 18 | C39: 7.25
A40: Jose | B40: 18 | C40: 7.25
A41: Maura | B41: 18 | C41: 7.25
A42: David | B42: 17 | C42: 7.25
A43: Felipe | B43: 17 | C43: 7.25

Sheet Materials
A1: Solvents | C1: Cost | D1: Unit | E1: Per Gal
A2: VM&P Natha | C2: 190 | D2: 55 | E2: =C2/D2 -> 3.4545455
A3: Xylene | C3: 260 | D3: 55 | E3: =C3/D3 -> 4.7272727
A5: Fabric | B5: Width | C5: Cost | D5: Unit
B6: 4" | C6: 26.73 | D6: 300
B7: 6" | C7: 37 | D7: 300
B8: 9" | C8: 44 | D8: 300
B9: 12" | C9: 53.03 | D9: 300
B10: 18" | C10: 79.17 | D10: 300
B11: 36" | C11: 120 | D11: 300
B12: 48" | C12: 150 | D12: 300
A14: Board | B14: Thickness | C14: Cost | D14: Truckload | E14: Unit
A15: Dens Deck | B15: 0.25" | C15: 36.5 | E15: Square
A16: Blackboard | B16: .5" | C16: 26.78 | D16: 24.5 | E16: Square
A17: Type X Gyp. Brd | B17: .5" | C17: 30 | D17: 28 | E17: Square
A18: ISO board | B18: 1" | C18: 47.38 | D18: 42.25 | E18: Square
A19: ISO board | B19: 1.5" | C19: 58.11 | D19: 48.33 | E19: Square
A20: ISO board | B20: 2" | C20: 77.47 | D20: 64.5 | E20: Square
A21: ISO board | B21: 3" | C21: 88 | D21: 73 | E21: Square
A24: Fasteners | B24: Length | C24: Cost | D24: Unit
A25: Metal Screws | B25: 3.25 | C25: 90.05 | D25: 1000
B26: 3.75 | C26: 98.47 | D26: 1000
B27: 4.5 | C27: 117.15 | D27: 1000
B28: 5 | C28: 140.37 | D28: 1000
B29: 6 | C29: 172.67 | D29: 1000
B30: 7 | C30: 244.79 | D30: 1000
B31: 8 | C31: 276.01 | D31: 1000
B32: >8 | C32: call for pricing
A34: Plates
A35: Carlisle | C35: 79.05 | D35: 1000

Sheet General

Sheet Performance & Payment Bonds
A1: Project Total
B3: =IF(B1<=100000,B1*0.0225,"") -> 0 | C3: =IF(AND(B1<=500000,B1>100000), ((B1-100000)*0.015)+2250,"") | D3: =IF(AND(B1<=2500000,B1>500000), ((B1-500000)*0.0105)+8250,"")
