Workbook
Name Coating_Databas: [1]Estimate!#REF!
Name Coating_Databas: Estimate!#REF!

Sheet Estimate
B1: Today's Date: | C1: 45847 | F1: Bill To Address:
B2: Job Name: | C2: Boone - McCall Residence | F2: City, State, Zip:
B3: Job Type: | C3: Insulation - Walls Only | F3: Contact:
B4: Site Address: | C4: 2333 Todds Point Rd. | F4: Email Address:
B5: City, State, Zip: | C5: Simpsonville, KY | F5: Phone:
B6: Contact: | C6: Dillon Boone | F6: Fax:
B7: Title:
B8: Email Address:
B9: Phone:
A11: Est. Square Feet:
A12: Materials | C12: 2637 | D12: ='Sq Ft Calculation'!F15 -> 0
A13: *
B14: Type | C14: Sq. Ft. | E14: Unit Price | G14: Est. Units | H14: Est. Cost
A16: Foam | B16: Mfg: | C16: Gaco = 1, NCFI = 2, BASF = 3, PSI = 4, Demilec = 5
B17: Types: | C17: 2.0 lb. = 1, 0.5 lb. = 2
D18: Thickness
A19: 11 | B19: =IF(A19=11,"Gaco 2.0 lb.",IF(A19=12,"Gaco 0.5 lb.",IF(A19=21,"NCFI 2.0 lb.",IF(A19=22,"NCFI 0.5 lb.",IF(A19=31,"BASF 2.0 lb.",IF(A19=32,"BASF 0.5 lb.",IF(A19=41,"PSI 2.0 lb.",IF(A19=42,"PSI 0.5 lb.",IF(A19=51,"Demilec 2.0 lb.",IF(A19=52,"Demilec 0.5 lb.","")))))))))) -> Gaco 2.0 lb. | C19: 2800 | D19: 4.25 | E19: 1.63 | F19: 13500 | G19: =((C19/F19)*D19)*1000 -> 881.48148 | H19: =E19*G19 -> 1436.8148
A20: 11 | B20: =IF(A20=11,"Gaco 2.0 lb.",IF(A20=12,"Gaco 0.5 lb.",IF(A20=21,"NCFI 2.0 lb.",IF(A20=22,"NCFI 0.5 lb.",IF(A20=31,"BASF 2.0 lb.",IF(A20=32,"BASF 0.5 lb.",IF(A20=41,"PSI 2.0 lb.",IF(A20=42,"PSI 0.5 lb.",IF(A20=51,"Demilec 2.0 lb.",IF(A20=52,"Demilec 0.5 lb.","")))))))))) -> Gaco 2.0 lb. | C20: 0 | D20: 2 | E20: 2.2 | F20: 3500 | G20: =((C20/F20)*D20)*1000 -> 0 | H20: =E20*G20 -> 0
A21: 11 | B21: =IF(A21=11,"Gaco 2.0 lb.",IF(A21=12,"Gaco 0.5 lb.",IF(A21=21,"NCFI 2.0 lb.",IF(A21=22,"NCFI 0.5 lb.",IF(A21=31,"BASF 2.0 lb.",IF(A21=32,"BASF 0.5 lb.",IF(A21=41,"PSI 2.0 lb.",IF(A21=42,"PSI 0.5 lb.",IF(A21=51,"Demilec 2.0 lb.",IF(A21=52,"Demilec 0.5 lb.","")))))))))) -> Gaco 2.0 lb. | C21: 0 | D21: 2 | E21: 2.2 | F21: 3500 | G21: =((C21/F21)*D21)*1000 -> 0 | H21: =E21*G21 -> 0
C23: Linear Ft.
A24: Membrane | C24: 0 | E24: 0.75 | H24: =C24*E24 -> 0
A26: Primer | C26: 0 | E26: 30 | G26: =C26/250 -> 0 | H26: =E26*G26 -> 0
A28: Coating | B28: Types: | C28: DC 315 TB = 1, Acrylic = 2, NoBurn TB = 3
C29: Sq. Ft. | D29: Gal / Sq.
A30: 1 | B30: =IF(A30=1,"DC 315 TB",IF(A30=2,"Acrylic",IF(A30=3,"NoBurn TB",""))) -> DC 315 TB | C30: 0 | D30: 1.5 | E30: 52 | G30: =(((C30/100)*D30))/((100-A$34)/100) -> 0 | H30: =E30*G30 -> 0
A31: 1 | B31: =IF(A31=1,"DC 315 TB",IF(A31=2,"Acrylic",IF(A31=3,"NoBurn TB",""))) -> DC 315 TB | C31: 0 | D31: 1.5 | E31: 52 | G31: =(((C31/100)*D31))/((100-A$34)/100) -> 0 | H31: =E31*G31 -> 0
A32: 1 | B32: =IF(A32=1,"DC 315 TB",IF(A32=2,"Acrylic",IF(A32=3,"NoBurn TB",""))) -> DC 315 TB | C32: 0 | D32: 1.5 | E32: 52 | G32: =(((C32/100)*D32))/((100-A$34)/100) -> 0 | H32: =E32*G32 -> 0
A33: Margin %:
A34: 20
A36: Thinner | B36: Types: | C36: Naphtha VM&P = 1, Mineral Spirits = 2, Xylene= 3
A37: 1 | B37: =IF(A37=1,"Naphtha VM&P",IF(A37=2,"Mineral Spirits",IF(A37=3,"Xylene",""))) -> Naphtha VM&P | E37: 10 | G37: =((G30+G31+G32)/55)*4 -> 0 | H37: =E37*G37 -> 0
A39: Caulk/Sealant | B39: Types: | C39: Can Foam = 1, Liquid Flashing = 2, Pointing Mastic = 3
C40: Linear Ft. | D40: Ft. / Unit
A41: 2 | B41: =IF(A41=1,"Can Foam",IF(A41=2,"Liquid Flashing",IF(A41=3,"Pointing Mastic",""))) -> Liquid Flashing | C41: 0 | D41: 0 | E41: 20 | G41: =IF(D41=0,0,C41/D41) -> 0 | H41: =G41*E41 -> 0
A43: 3 | B43: =IF(A43=1,"Can Foam",IF(A43=2,"Liquid Flashing",IF(A43=3,"Pointing Mastic",""))) -> Pointing Mastic | C43: 0 | D43: 0 | E43: 10 | G43: =IF(D43=0,0,C43/D43) -> 0 | H43: =G43*E43 -> 0
A45: Lift | B45: Types: | C45: Forklift = 1, Boom = 2, Scissor = 3, Articulating = 4
C46: Size | D46: Period | F46: Margin %
A47: 1 | B47: =IF(A47=1,"Forklift",IF(A47=2,"Boom",IF(A47=3,"Scissor",IF(A47=4,"Articulating","")))) -> Forklift | C47: 20' | D47: 0 | E47: 0 | F47: 20 | H47: =D47*E47*(1+(F47/100)) -> 0
A48: 1 | B48: =IF(A48=1,"Forklift",IF(A48=2,"Boom",IF(A48=3,"Scissor",IF(A48=4,"Articulating","")))) -> Forklift | C48: 20' | D48: 0 | E48: 0 | F48: 20 | H48: =D48*E48*(1+(F48/100)) -> 0
A50: Delivery Fee | E50: 0 | G50: 0 | H50: =E50*G50 -> 0
C52: Est. Days
A53: Generator | C53: 3 | E53: 40 | H53: =C53*E53 -> 120
A55: Space Heater | C55: 0 | E55: 40 | H55: =C55*E55 -> 0
A57: Misc. | E57: 0 | H57: =E57 -> 0
A59: Freight | E59: 0 | H59: =E59 -> 0
A61: ABAA Audits | E61: 2000 | G61: 0 | H61: =E61*G61 -> 0
A63: ABAA Fee | G63: =C12 -> 2637 | H63: =E63*G63 -> 0
A65: Drum Disp. | E65: 0 | G65: =(((G26+G30+G31+G32+G37)/50)+(G19+G20+G21)/500)+1 -> 2.762963 | H65: =E65*G65 -> 0
B67: No. of Trips | C67: R.T. Miles
A68: Sales/Inspect. | B68: 2 | C68: 20 | E68: 0.65 | H68: =B68*C68*E68 -> 26
A70: Truck Exp. | B70: 2 | C70: 20 | E70: 1.15 | H70: =B70*C70*E70 -> 46
H71: *****************
G72: Subtotal Materials | H72: =SUM(H19:H70) -> 1628.8148
F73: Sales Tax % | G73: 0.06 | H73: =(H72*G73) -> 97.728889
A74: Labor / Subcontractor
A75: *
B76: Days | C76: No. of People | D76: Total Hours | E76: Prevailing Wage | F76: Fringe | G76: Total Prevailing Wage | H76: Est. Cost | J76: Daily Rate
A78: Set Up | B78: 0.1 | C78: 3 | D78: =(B78*People!B11)*C78 -> 3 | G78: =(E78+F78)*People!C3 -> 0 | H78: =IF(G78=0, B78*J78, D78*G78) -> 93.6 | J78: =IF(C78=1,People!$D$12)+IF(C78=2,People!$E$12)+IF(C78=3,People!$F$12)+IF(C78=4,People!$G$12)+IF(C78=5,People!$H$12)+IF(C78=6,People!$I$12)+IF(C78=7,People!$J$12)+IF(C78=8,People!$K$12) -> 936
A80: Mask | B80: 0.25 | C80: 3 | D80: =(B80*People!B11)*C80 -> 7.5 | G80: =(E80+F80)*People!C3 -> 0 | H80: =IF(G80=0, B80*J80, D80*G80) -> 234 | J80: =IF(C80=1,People!D12)+IF(C80=2,People!E12)+IF(C80=3,People!F12)+IF(C80=4,People!G12)+IF(C80=5,People!H12)+IF(C80=6,People!I12)+IF(C80=7,People!J12)+IF(C80=8,People!K12) -> 936
A82: Prime | D82: =(B82*People!B11)*C82 -> 0 | G82: =(E82+F82)*People!C3 -> 0 | H82: =IF(G82=0, B82*J82, D82*G82) -> 0 | J82: =IF(C82=1,People!D12)+IF(C82=2,People!E12)+IF(C82=3,People!F12)+IF(C82=4,People!G12)+IF(C82=5,People!H12)+IF(C82=6,People!I12)+IF(C82=7,People!J12)+IF(C82=8,People!K12) -> 0
A84: Membrane | D84: =(B84*People!B11)*C84 -> 0 | G84: =(E84+F84)*People!C3 -> 0 | H84: =IF(G84=0, B84*J84, D84*G84) -> 0 | J84: =IF(C84=1,People!D12)+IF(C84=2,People!E12)+IF(C84=3,People!F12)+IF(C84=4,People!G12)+IF(C84=5,People!H12)+IF(C84=6,People!I12)+IF(C84=7,People!J12)+IF(C84=8,People!K12) -> 0
A86: Foam | B86: 1.5 | C86: 3 | D86: =(B86*People!B11)*C86 -> 45 | G86: =(E86+F86)*People!C3 -> 0 | H86: =IF(G86=0, B86*J86, D86*G86) -> 1404 | J86: =IF(C86=1,People!D12)+IF(C86=2,People!E12)+IF(C86=3,People!F12)+IF(C86=4,People!G12)+IF(C86=5,People!H12)+IF(C86=6,People!I12)+IF(C86=7,People!J12)+IF(C86=8,People!K12) -> 936
A88: DC 315 | D88: =(B88*People!B11)*C88 -> 0 | G88: =(E88+F88)*People!C3 -> 0 | H88: =IF(G88=0, B88*J88, D88*G88) -> 0 | J88: =IF(C88=1,People!D12)+IF(C88=2,People!E12)+IF(C88=3,People!F12)+IF(C88=4,People!G12)+IF(C88=5,People!H12)+IF(C88=6,People!I12)+IF(C88=7,People!J12)+IF(C88=8,People!K12) -> 0
A90: Misc. | D90: =(B90*People!B11)*C90 -> 0 | G90: =(E90+F90)*People!C3 -> 0 | H90: =IF(G90=0, B90*J90, D90*G90) -> 0 | J90: =IF(C90=1,People!D12)+IF(C90=2,People!E12)+IF(C90=3,People!F12)+IF(C90=4,People!G12)+IF(C90=5,People!H12)+IF(C90=6,People!I12)+IF(C90=7,People!J12)+IF(C90=8,People!K12) -> 0
A92: Clean Up | B92: 0.15 | C92: 3 | D92: =(B92*People!B11)*C92 -> 4.5 | G92: =(E92+F92)*People!C3 -> 0 | H92: =IF(G92=0, B92*J92, D92*G92) -> 140.4 | J92: =IF(C92=1,People!D12)+IF(C92=2,People!E12)+IF(C92=3,People!F12)+IF(C92=4,People!G12)+IF(C92=5,People!H12)+IF(C92=6,People!I12)+IF(C92=7,People!J12)+IF(C92=8,People!K12) -> 936
C94: Est. Hours / Day | E94: No. of People | G94: Est. Rate
A95: Loading | C95: 1 | E95: 1 | G95: 25.5 | H95: =IF(E95=1,People!B3*C95,IF(E95=2,(People!B3+People!B4)*C95,))*B70 -> 66
A97: Traveling | C97: 1 | E97: 3 | G97: 13 | H97: =C97*E97*G97*B70 -> 78
C99: No. of Days
A100: Meals, Lodging Expenses | G100: 125 | H100: =C100*E100*G100 -> 0
A102: * | H102: *
A103: Total Hours | B103: =D78+D80+D82+D84+D86+D88+D90+D92+((C95*E95)+(C97*E97))*B70 -> 68 | C103: Total Days | D103: =SUM(B78:B95) -> 2 | G103: Subtotal Labor / Subcontractor | H103: =SUM(H78:H100) -> 2016
A105: Bonding and Insurance
A106: *
H107: Est. Cost
A109: Miscellaneous Insurance | E109: Est. Cost | F109: 0 | H109: =F109 -> 0
A111: Permits | B111: Describe: | E111: Est. Cost | F111: 0 | H111: =F111 -> 0
H113: *
G114: Subtotal Warranty, Bonding, Insurance | H114: =H109+H111 -> 0
H115: *
A116: Total Job Cost | H116: =H72+H103+H114 -> 3644.8148
A118: Estimated O/H | E118: Percentage: | F118: 30 | H118: =H116*(F118/100) -> 1093.4444
A120: Profit | E120: Percentage: | F120: 10 | H120: =(H116+H118)*(F120/100) -> 473.82593
H121: *
A122: Work Sheet Price | H122: =SUM(H73+H116+H118+H120) -> 5309.8141
A123: Work Sheet Price + Additional Amount w/o Markup | F123: 5860 | H123: =H122+SUM(F125:F134) -> 5859.8141
H124: *
A126: Misc | F126: 550
A127: Additional Amount w/o Markup
A128: Additional Amount w/o Markup
A129: Additional Amount w/o Markup
A130: Additional Amount w/o Markup
A131: Additional Amount w/o Markup
A132: Additional Amount w/o Markup
A133: Additional Amount w/o Markup
A135: Summary
A137: Price / Sq. Ft: | B137: =H123/C12 -> 2.2221517 | C137: Est. Sets: | D137: =SUM((G19+G20+G21)/1000) -> 0.88148148

Sheet People
E1: Crew Size
A2: Job Classification | B2: Hourly Wage | C2: Burden Rate | D2: 1 | E2: 2 | F2: 3 | G2: 4 | H2: 5 | I2: 6 | J2: 7 | K2: 8
A3: Foreman / Sprayer | B3: 33 | C3: 1.2 | D3: =B3*C3 -> 39.6 | E3: =B3*C3 -> 39.6 | F3: =B3*C3 -> 39.6 | G3: =B3*C3 -> 39.6 | H3: =B3*C3 -> 39.6 | I3: =B3*C3 -> 39.6 | J3: =B3*C3 -> 39.6 | K3: =B3*C3 -> 39.6
A4: Sprayer / Trailer | B4: 23.5 | C4: 1.2 | E4: =B4*C4 -> 28.2 | F4: =B4*C4 -> 28.2 | G4: =B4*C4 -> 28.2 | H4: =B4*C4 -> 28.2 | I4: =B4*C4 -> 28.2 | J4: =B4*C4 -> 28.2 | K4: =B4*C4 -> 28.2
A5: Trailer / Hose | B5: 21.5 | C5: 1.2 | F5: =B5*C5 -> 25.8 | G5: =B5*C5 -> 25.8 | H5: =B5*C5 -> 25.8 | I5: =B5*C5 -> 25.8 | J5: =B5*C5 -> 25.8 | K5: =B5*C5 -> 25.8
A6: Hose / Laborer | B6: 21 | C6: 1.2 | G6: =B6*C6 -> 25.2 | H6: =B6*C6 -> 25.2 | I6: =B6*C6 -> 25.2 | J6: =B6*C6 -> 25.2 | K6: =B6*C6 -> 25.2
A7: Laborer | B7: 20 | C7: 1.2 | H7: =B7*C7 -> 24 | I7: =B7*C7 -> 24 | J7: =B7*C7 -> 24 | K7: =B7*C7 -> 24
A8: Laborer | B8: 20 | C8: 1.2 | I8: =B8*C8 -> 24 | J8: =B8*C8 -> 24 | K8: =B8*C8 -> 24
A9: Laborer | B9: 18 | C9: 1.2 | J9: =B9*C9 -> 21.6 | K9: =B9*C9 -> 21.6
A10: Laborer | B10: 18 | C10: 1.2 | K10: =B10*C10 -> 21.6
A11: Hours /Day | B11: 10
A12: Estimated Cost/Day | D12: =SUM(D3:D10)*B11 -> 396 | E12: =SUM(E3:E10)*B11 -> 678 | F12: =SUM(F3:F10)*B11 -> 936 | G12: =SUM(G3:G10)*B11 -> 1188 | H12: =SUM(H3:H10)*B11 -> 1428 | I12: =SUM(I3:I10)*B11 -> 1668 | J12: =SUM(J3:J10)*B11 -> 1884 | K12: =SUM(K3:K10)*B11 -> 2100
A15: Crew Leaders | B15: Hourly | C15: Travel
A16: Mariano Perez | B16: 33 | C16: 20
A17: Carlos Garcia | B17: 28 | C17: 20
A18: Abel Reyes | B18: 28 | C18: 20
A19: Miguel Avila | B19: 25 | C19: 10
A21: Workers | B21: Hourly | C21: Travel
A22: Hugo | B22: 28 | C22: 10
A23: Santos | B23: 25 | C23: 20
A24: Erik Avila | B24: 25 | C24: 12.5
A25: Michael | B25: 23.5 | C25: 11.75
A26: Juan Loa | B26: 23 | C26: 10
A27: Axel | B27: 23 | C27: 10
A28: Gilberto Morales | B28: 21 | C28: 8.75
A29: Melvin Lutin | B29: 20 | C29: 8
A30: Ramiro | B30: 20 | C30: 10
A31: Jesus | B31: 20 | C31: 7.25
A32: Onilson Morales | B32: 19.5 | C32: 8
A33: Frederico | B33: 19 | C33: 7.25
A34: Pedro Morales | B34: 18.5 | C34: 8
A37: TEMP Workers | B37: Hourly | C37: Travel
A38: Nelvi | B38: 19 | C38: 7.25
A39: Bryan | B39: 18 | C39: 7.25
A40: Jose | B40: 18 | C40: 7.25
A41: Maura | B41: 18 | C41: 7.25
A42: David | B42: 17 | C42: 7.25
A43: Felipe | B43: 17 | C43: 7.25

Sheet Materials
A1: Solvents | C1: Cost | D1: Unit | E1: Per Gal
A2: VM&P Natha | C2: 190 | D2: 55 | E2: =C2/D2 -> 3.4545455
A3: Xylene | C3: 260 | D3: 55 | E3: =C3/D3 -> 4.7272727
A5: Fabric | B5: Width | C5: Cost | D5: Unit
B6: 4" | C6: 27 | D6: 300
B7: 6" | C7: 37 | D7: 300
B8: 9" | C8: 44 | D8: 300
B9: 12" | C9: 54 | D9: 300
B10: 18" | C10: 80 | D10: 300
B11: 36" | C11: 120 | D11: 300
B12: 48" | C12: 150 | D12: 300
A14: Membrane | B14: Thickness | C14: Cost | D14: Unit
B15: 6" | C15: 22 | D15: 75
B16: 12" | C16: 42 | D16: 75
B17: 18" | C17: 62 | D17: 75
B18: 38.5" | C18: 124 | D18: 75

Sheet General

Sheet Sq Ft Calculation
B2: Description | C2: Height | D2: Width | E2: Total
B4: Wall | E4: =C4*D4 -> 0
E5: =C5*D5 -> 0
E6: =C6*D6 -> 0
E7: =C7*D7 -> 0
E8: =C8*D8 -> 0
B9: Ceiling | E9: =C9*D9 -> 0
E10: =C10*D10 -> 0
E11: =C11*D11 -> 0
E12: =C12*D12 -> 0
B13: Gables | E13: =(C13/2)*D13 -> 0
E14: =(C14/2)*D14 -> 0
E15: =C15*D15 -> 0 | F15: =SUM(E4:E15) -> 0

Sheet Performance & Payment Bonds
A1: Project Total
B3: =IF(B1<=100000,B1*0.0225,"") -> 0 | C3: =IF(AND(B1<=500000,B1>100000), ((B1-100000)*0.015)+2250,"") | D3: =IF(AND(B1<=2500000,B1>500000), ((B1-500000)*0.0105)+8250,"")
